cryptanalysis/__init__.py
cryptanalysis/characteristic_searcher.py
cryptanalysis/cryptanalysis.py
cryptanalysis/differential_cryptanalysis.py
cryptanalysis/linear_cryptanalysis.py
cryptanalysis/spn.py
cryptanalysis/utils.py
tests/__init__.py
tests/test_characteristic_searcher.py
tests/test_spn.py
tests/test_utils.py
cryptanalysis-0.0.3.dist-info/LICENSE.md
cryptanalysis-0.0.3.dist-info/METADATA
cryptanalysis-0.0.3.dist-info/WHEEL
cryptanalysis-0.0.3.dist-info/top_level.txt
cryptanalysis-0.0.3.dist-info/RECORD
