Metadata-Version: 2.1
Name: cryptanalysis
Version: 0.0.3
Summary: Automated cryptanalysis library for substitution permutation network
Home-page: https://github.com/deut-erium/auto-cryptanalysis
Author: Himanshu Sheoran
License: GPL
Project-URL: Documentation, https://deut-erium.github.io/auto-cryptanalysis
Project-URL: Source Code, https://github.com/deut-erium/auto-cryptanalysis
Keywords: cryptanalysis differential linear cryptography SPN cipher crypto
Classifier: License :: OSI Approved :: GNU General Public License v3 (GPLv3)
Classifier: Operating System :: OS Independent
Classifier: Programming Language :: Python :: 3
Classifier: Programming Language :: Python :: 3.6
Classifier: Programming Language :: Python :: 3.7
Classifier: Programming Language :: Python :: 3.8
Classifier: Programming Language :: Python :: 3.9
Classifier: Programming Language :: Python :: 3.10
Classifier: Programming Language :: Python :: 3.11
Requires-Python: >=3.6
License-File: LICENSE.md
Requires-Dist: z3-solver
Requires-Dist: tqdm
